pelican/plugins/md_include/__init__.py
pelican/plugins/md_include/md_include.py
pelican/plugins/md_include/test_md_include.py
pelican_markdown_include-1.0.6.dist-info/METADATA
pelican_markdown_include-1.0.6.dist-info/WHEEL
pelican_markdown_include-1.0.6.dist-info/entry_points.txt
pelican_markdown_include-1.0.6.dist-info/RECORD
