Metadata-Version: 2.1
Name: pelican-markdown-include
Version: 1.0.6
Summary: Pelican plugin for using the Markdown-Include extension
Keywords: pelican,plugin,markdown include
Author-Email: =?utf-8?q?Rafael_Laboissi=C3=A8re?= <rafael@laboissiere.net>
License: AGPL-3.0
Classifier: Development Status :: 5 - Production/Stable
Classifier: Environment :: Console
Classifier: Framework :: Pelican
Classifier: Framework :: Pelican :: Plugins
Classifier: Intended Audience :: End Users/Desktop
Classifier: License :: OSI Approved :: GNU Affero General Public License v3
Classifier: Operating System :: OS Independent
Classifier: Programming Language :: Python :: 3
Classifier: Programming Language :: Python :: 3.10
Classifier: Programming Language :: Python :: 3.11
Classifier: Programming Language :: Python :: 3.12
Classifier: Programming Language :: Python :: 3.13
Classifier: Programming Language :: Python :: 3.14
Classifier: Topic :: Internet :: WWW/HTTP
Classifier: Topic :: Software Development :: Libraries :: Python Modules
Project-URL: Homepage, https://github.com/pelican-plugins/markdown-include
Project-URL: Issue Tracker, https://github.com/pelican-plugins/markdown-include/issues
Project-URL: Changelog, https://github.com/pelican-plugins/markdown-include/blob/main/CHANGELOG.md
Project-URL: Funding, https://donate.getpelican.com/
Requires-Python: >=3.10
Requires-Dist: pelican>=4.5
Requires-Dist: py3dns>=3.2
Requires-Dist: markdown>=3.4
Requires-Dist: markdown-include>=0.8
Provides-Extra: markdown
Requires-Dist: markdown>=3.4; extra == "markdown"
